orca_sph.libs/libGrpcRuntime-3f76c831.so.1.0.0
orca_sph.libs/libParticleRenderClient-b96e96a6.so.1.0.0
orca_sph.libs/libcap-0e62ac39.so.2.66
orca_sph.libs/libdbus-1-a6ae7b4e.so.3.32.4
orca_sph.libs/libgcrypt-f207cbaa.so.20.4.3
orca_sph.libs/libgomp-16c68465.so.1.0.0
orca_sph.libs/libgpg-error-6cb18a00.so.0.34.0
orca_sph.libs/liblz4-40bffd0a.so.1.9.4
orca_sph.libs/liblzma-a9793942.so.5.4.5
orca_sph.libs/libsystemd-c489a13c.so.0.38.0
orca_sph.libs/libzstd-0a2128bc.so.1.5.5
orcasph_client/__init__.py
orcasph_client/cli.py
orcasph_client/bin/SPHSimulator
orcasph_client/bin/config.json
orcasph_client/lib/libGrpcRuntime.so.1.0.0
orcasph_client/lib/libMD5.a
orcasph_client/lib/libOrcaLinkBridge.a
orcasph_client/lib/libParticleRenderBridge.a
orcasph_client/lib/libParticleRenderClient.so.1.0.0
orcasph_client/lib/libSPlisHSPlasH.a
orcasph_client/lib/libSimulatorBase.a
orcasph_client/lib/libUtilities.a
orcasph_client/lib/libglfw3.a
orcasph_client/lib/libimgui.a
orcasph_client/lib/libnfd.a
orcasph_client/lib/libpartio.a
orcasph_client/lib/libtinyexpr.a
orcasph_client/lib/libzlib.a
orca_sph-26.1.3.dist-info/METADATA
orca_sph-26.1.3.dist-info/WHEEL
orca_sph-26.1.3.dist-info/entry_points.txt
orca_sph-26.1.3.dist-info/top_level.txt
orca_sph-26.1.3.dist-info/licenses/LICENSE
orca_sph-26.1.3.dist-info/sboms/auditwheel.cdx.json
orca_sph-26.1.3.dist-info/RECORD
