Metadata-Version: 2.4
Name: orca-sph
Version: 26.1.3
Summary: OrcaSPH - SPH Fluid Simulator with OrcaLink Integration
Home-page: https://github.com/your-repo/OrcaSPH
Author: OrcaSPH Team
Author-email: 
License-Expression: LicenseRef-Proprietary
Keywords: sph,fluids,simulation,orca,orcalink,fluid-dynamics
Classifier: Development Status :: 4 - Beta
Classifier: Intended Audience :: Developers
Classifier: Intended Audience :: Science/Research
Classifier: Operating System :: POSIX :: Linux
Classifier: Programming Language :: Python :: 3
Classifier: Programming Language :: Python :: 3.10
Classifier: Programming Language :: Python :: 3.11
Classifier: Programming Language :: Python :: 3.12
Classifier: Programming Language :: Python :: 3.13
Classifier: Topic :: Scientific/Engineering
Classifier: Topic :: Scientific/Engineering :: Physics
Classifier: Topic :: Software Development :: Libraries :: Python Modules
Requires-Python: >=3.10
License-File: LICENSE
Requires-Dist: orca-link==26.1.3
Provides-Extra: dev
Requires-Dist: pytest; extra == "dev"
Requires-Dist: pytest-cov; extra == "dev"
Requires-Dist: black; extra == "dev"
Requires-Dist: flake8; extra == "dev"
Dynamic: home-page
Dynamic: license-file
Dynamic: requires-python
